ensembleset/__init__.py
ensembleset/dataset.py
ensembleset/feature_engineerings.py
ensembleset/feature_methods.py
ensembleset/preprocessing_methods.py
ensembleset-1.0a19.dist-info/METADATA
ensembleset-1.0a19.dist-info/WHEEL
ensembleset-1.0a19.dist-info/licenses/LICENSE
ensembleset-1.0a19.dist-info/RECORD
