Metadata-Version: 2.4
Name: ensembleset
Version: 1.0a19
Summary: Ensemble dataset generator for tabular data prediction and modeling projects.
Project-URL: Homepage, https://github.com/gperdrizet/ensembleset
Project-URL: Issues, https://github.com/gperdrizet/ensembleset/issues
Author-email: George Perdrizet <george@perdrizet.org>
License-Expression: GPL-3.0-or-later
License-File: LICENSE
Classifier: Operating System :: OS Independent
Classifier: Programming Language :: Python :: 3
Requires-Python: >=3.10
Requires-Dist: h5py
Requires-Dist: numpy
Requires-Dist: pandas
Requires-Dist: scikit-learn
